eegwlib/__init__.py
eegwlib/artifact_detection.py
eegwlib/average.py
eegwlib/filter.py
eegwlib/mffpy.py
eegwlib/segment.py
eegwlib/write.py
eegwlib/mffpy/__init__.py
eegwlib/mffpy/bin_files.py
eegwlib/mffpy/reader.py
eegwlib/mffpy/segmentation.py
eegwlib/segmentation/__init__.py
eegwlib/segmentation/bin_files.py
eegwlib/segmentation/segmenter.py
eegwlib/segmentation/utils.py
eegwlib-0.1.3.dist-info/LICENSE
eegwlib-0.1.3.dist-info/METADATA
eegwlib-0.1.3.dist-info/WHEEL
eegwlib-0.1.3.dist-info/top_level.txt
eegwlib-0.1.3.dist-info/RECORD
