Metadata-Version: 2.1
Name: eegwlib
Version: 0.1.3
Summary: Helper functions for EEG workflows
Home-page: UNKNOWN
Author: Evan Hathaway
Author-email: evan.hathaway@bel.company
License: UNKNOWN
Platform: UNKNOWN
License-File: LICENSE
